llm_analysis/__init__.py
llm_analysis/analysis.py
llm_analysis/config.py
llm_analysis/constant.py
llm_analysis/dtype_configs/w16a16e16.json
llm_analysis/dtype_configs/w16a16e32.json
llm_analysis/dtype_configs/w4a16e16.json
llm_analysis/dtype_configs/w4a16e32.json
llm_analysis/dtype_configs/w4a4e16.json
llm_analysis/dtype_configs/w4a4e32.json
llm_analysis/dtype_configs/w4a8e16.json
llm_analysis/dtype_configs/w4a8e32.json
llm_analysis/dtype_configs/w8a16e16.json
llm_analysis/dtype_configs/w8a16e32.json
llm_analysis/dtype_configs/w8a8e16.json
llm_analysis/dtype_configs/w8a8e32.json
llm_analysis/gpu_configs/a10-pcie-28gb.json
llm_analysis/gpu_configs/a100-pcie-40gb.json
llm_analysis/gpu_configs/a100-pcie-80gb.json
llm_analysis/gpu_configs/a100-sxm-40gb.json
llm_analysis/gpu_configs/a100-sxm-80gb.json
llm_analysis/gpu_configs/a10g-pcie-24gb.json
llm_analysis/gpu_configs/a6000-48gb.json
llm_analysis/gpu_configs/h100-pcie-80gb.json
llm_analysis/gpu_configs/h100-sxm-80gb.json
llm_analysis/gpu_configs/mi100-32gb.json
llm_analysis/gpu_configs/mi210-64gb.json
llm_analysis/gpu_configs/mi250-128gb.json
llm_analysis/gpu_configs/mi250x-128gb.json
llm_analysis/gpu_configs/v100-pcie-16gb.json
llm_analysis/gpu_configs/v100-pcie-32gb.json
llm_analysis/gpu_configs/v100-sxm-16gb.json
llm_analysis/gpu_configs/v100-sxm-32gb.json
llm_analysis/logger.py
llm_analysis/model_configs/EleutherAI_gpt-j-6b.json
llm_analysis/model_configs/EleutherAI_gpt-neo-1.3B.json
llm_analysis/model_configs/EleutherAI_gpt-neo-125m.json
llm_analysis/model_configs/EleutherAI_gpt-neo-2.7B.json
llm_analysis/model_configs/NousResearch_Llama-2-7b-hf.json
llm_analysis/model_configs/PygmalionAI_pygmalion-6b.json
llm_analysis/model_configs/allenai_scibert_scivocab_uncased.json
llm_analysis/model_configs/bert-base-cased.json
llm_analysis/model_configs/bert-base-multilingual-cased.json
llm_analysis/model_configs/bert-base-uncased.json
llm_analysis/model_configs/bert-large.json
llm_analysis-0.2.2.dist-info/LICENSE
llm_analysis-0.2.2.dist-info/METADATA
llm_analysis-0.2.2.dist-info/WHEEL
llm_analysis-0.2.2.dist-info/RECORD
