Metadata-Version: 2.1
Name: llm-analysis
Version: 0.2.2
Summary: Latency and Memory Analysis of Transformer Models for Training and Inference
License: Apache License, Version 2.0
Author: Cheng Li
Author-email: pistasable@gmail.com
Requires-Python: >=3.8,<4.0
Classifier: License :: Other/Proprietary License
Classifier: Programming Language :: Python :: 3
Classifier: Programming Language :: Python :: 3.8
Classifier: Programming Language :: Python :: 3.9
Classifier: Programming Language :: Python :: 3.10
Classifier: Programming Language :: Python :: 3.11
Classifier: Programming Language :: Python :: 3.12
Requires-Dist: fire (>=0.5.0,<0.6.0)
Requires-Dist: huggingface-hub (>=0.14.1,<0.15.0)
Requires-Dist: transformers (>=4.28.1,<5.0.0)
